packageint/__init__.py
packageint-0.1.dist-info/Licence.txt
packageint-0.1.dist-info/METADATA
packageint-0.1.dist-info/WHEEL
packageint-0.1.dist-info/top_level.txt
packageint-0.1.dist-info/RECORD
