Metadata-Version: 2.1
Name: packageint
Version: 0.1
Summary: This is code
Author: Int-209
License-File: Licence.txt
